webhooksimple/__init__.py
webhooksimple/__main__.py
webhooksimple/manager.py
webhooksimple/models.py
webhooksimple/parser.py
webhooksimple-0.1.1.dist-info/AUTHORS.rst
webhooksimple-0.1.1.dist-info/LICENSE
webhooksimple-0.1.1.dist-info/METADATA
webhooksimple-0.1.1.dist-info/WHEEL
webhooksimple-0.1.1.dist-info/top_level.txt
webhooksimple-0.1.1.dist-info/RECORD
