Metadata-Version: 2.1
Name: webhooksimple
Version: 0.1.1
Summary: A simple framework/cli tool to setup and sync (Webex Teams) API webhooks
Home-page: https://github.com/CiscoSE/webhooksimple
Author: Marcel Neidinger
Author-email: mneiding@cisco.com
License: MIT license
Keywords: webhooksimple
Platform: UNKNOWN
Classifier: Development Status :: 2 - Pre-Alpha
Classifier: Intended Audience :: Developers
Classifier: License :: OSI Approved :: MIT License
Classifier: Natural Language :: English
Classifier: Programming Language :: Python :: 2
Classifier: Programming Language :: Python :: 2.7
Classifier: Programming Language :: Python :: 3
Classifier: Programming Language :: Python :: 3.4
Classifier: Programming Language :: Python :: 3.5
Classifier: Programming Language :: Python :: 3.6
Classifier: Programming Language :: Python :: 3.7
Requires-Dist: pyyaml
Requires-Dist: webexteamssdk
Requires-Dist: jinja2
